{
  "tasks": [
    {
      "id": 1,
      "title": "Projet React MyStudyPlanner",
      "description": "Développer l'application web de gestion de devoirs",
      "subject": "Programmation Web",
      "priority": "haute",
      "status": "en cours",
      "dueDate": "2026-02-28",
      "createdAt": "2026-02-14T10:00:00.000Z"
    },
    {
      "id": 2,
      "title": "TP Node.js et Express",
      "description": "Créer une API REST avec Express et stockage JSON",
      "subject": "Backend",
      "priority": "haute",
      "status": "terminé",
      "dueDate": "2026-02-15",
      "createdAt": "2026-02-13T09:00:00.000Z"
    },
    {
      "id": 3,
      "title": "Réviser bases de données",
      "description": "Réviser les requêtes SQL et les jointures pour l'examen",
      "subject": "Base de données",
      "priority": "moyenne",
      "status": "en cours",
      "dueDate": "2026-02-25",
      "createdAt": "2026-02-15T14:00:00.000Z"
    },
    {
      "id": 4,
      "title": "Devoir Algorithmes",
      "description": "Exercices sur les arbres binaires et les graphes",
      "subject": "Algorithmique",
      "priority": "haute",
      "status": "non commencé",
      "dueDate": "2026-02-24",
      "createdAt": "2026-02-16T08:00:00.000Z"
    },
    {
      "id": 7,
      "title": "Présentation anglais",
      "description": "Préparer exposé oral sur les nouvelles technologies",
      "subject": "Anglais",
      "priority": "basse",
      "status": "terminé",
      "dueDate": "2026-02-17",
      "createdAt": "2026-02-10T09:00:00.000Z"
    },
    {
      "id": 8,
      "title": "TP Réseaux",
      "description": "Configuration routeurs et protocoles TCP/IP",
      "subject": "Réseaux",
      "priority": "moyenne",
      "status": "en cours",
      "dueDate": "2026-02-26",
      "createdAt": "2026-02-15T11:00:00.000Z"
    },
    {
      "id": 1771432087865,
      "title": "hhhh",
      "description": "jjjjj",
      "subject": "Programmation Web",
      "priority": "basse",
      "status": "en cours",
      "createdAt": "2026-02-18T16:28:07.865Z"
    }
  ]
}